wconv/__init__.py
wconv/ace.py
wconv/acl.py
wconv/helpers.py
wconv/main.py
wconv/objecttype.py
wconv/sddl.py
wconv/securitydescriptor.py
wconv/sid.py
wconv/uac.py
wconv-2.0.0.dist-info/METADATA
wconv-2.0.0.dist-info/WHEEL
wconv-2.0.0.dist-info/entry_points.txt
wconv-2.0.0.dist-info/licenses/LICENSE
wconv-2.0.0.dist-info/RECORD
