Metadata-Version: 2.4
Name: wconv
Version: 2.0.0
Summary: Windows Format Converter
Project-URL: Homepage, https://github.com/qtc-de/wconv
Project-URL: Documentation, https://github.com/qtc-de/wconv/tree/main/README.md
Project-URL: Repository, https://github.com/qtc-de/wconv
Project-URL: Bug Tracker, https://github.com/qtc-de/wconv/issues
Project-URL: Changelog, https://github.com/qtc-de/wconv/blob/main/CHANGELOG.md
Author: Tobias Neitzel (@qtc_de)
Maintainer: Tobias Neitzel (@qtc_de)
License:                     GNU GENERAL PUBLIC LICENSE
License-File: LICENSE
Keywords: ace,acl,ntsecuritydescriptor,sddl,securitydescriptor,sid,uac,windows
Classifier: License :: OSI Approved :: GNU General Public License v3 (GPLv3)
Classifier: Operating System :: Unix
Classifier: Programming Language :: Python :: 3
Requires-Python: >=3.9
Requires-Dist: colorama
